streamlit_monaco_copilot/__init__.py
streamlit_monaco_copilot/example.py
streamlit_monaco_copilot/frontend/build/asset-manifest.json
streamlit_monaco_copilot/frontend/build/bootstrap.min.css
streamlit_monaco_copilot/frontend/build/index.html
streamlit_monaco_copilot/frontend/build/static/js/main.7d2b5d60.js
streamlit_monaco_copilot/frontend/build/static/js/main.7d2b5d60.js.LICENSE.txt
streamlit_monaco_copilot/frontend/build/static/js/main.7d2b5d60.js.map
streamlit_monaco_copilot-0.0.1.dist-info/LICENSE
streamlit_monaco_copilot-0.0.1.dist-info/METADATA
streamlit_monaco_copilot-0.0.1.dist-info/WHEEL
streamlit_monaco_copilot-0.0.1.dist-info/top_level.txt
streamlit_monaco_copilot-0.0.1.dist-info/RECORD
