Metadata-Version: 2.1
Name: streamlit-monaco-copilot
Version: 0.0.1
Summary: Streamlit component that allows you to build your own simple github copilot
Home-page: https://github.com/liuhetian/streamlit-monaco-copilot
Author: Liu-Hetian
Author-email: 80733866@qq.com
Requires-Python: >=3.7
License-File: LICENSE
Requires-Dist: streamlit >=0.63
Provides-Extra: devel
Requires-Dist: wheel ; extra == 'devel'
Requires-Dist: pytest ==7.4.0 ; extra == 'devel'
Requires-Dist: playwright ==1.48.0 ; extra == 'devel'
Requires-Dist: requests ==2.31.0 ; extra == 'devel'
Requires-Dist: pytest-playwright-snapshot ==1.0 ; extra == 'devel'
Requires-Dist: pytest-rerunfailures ==12.0 ; extra == 'devel'
